tests
zpython_tools
