Metadata-Version: 1.1
Name: zpython-tools
Version: 0.0.8
Summary: kafka tools with python
Home-page: UNKNOWN
Author: Tony Liu
Author-email: UNKNOWN
License: UNKNOWN
Keywords: kafka tools built against our env.
Platform: UNKNOWN
Classifier: Development Status :: 4 - Beta
Classifier: Programming Language :: Python
Classifier: Programming Language :: Python :: 2.6
Classifier: Environment :: Console
Classifier: Intended Audience :: Developers
Classifier: Intended Audience :: System Administrators
Classifier: Operating System :: POSIX
Classifier: Operating System :: MacOS :: MacOS X
